reflexions/__init__.py
reflexions/cards.py
reflexions/iconify.py
reflexions/loading_icon.py
reflexions/pdf.py
reflexions/py.typed
reflexions/slider.py
reflexions/model_form/__init__.py
reflexions/model_form/base.py
reflexions/model_form/number_handlers.py
reflexions/model_form/union_handler.py
reflexions/model_form/utils.py
reflexions-0.1.1.dist-info/METADATA
reflexions-0.1.1.dist-info/WHEEL
reflexions-0.1.1.dist-info/licenses/LICENSE
reflexions-0.1.1.dist-info/RECORD
