Metadata-Version: 2.4
Name: reflexions
Version: 0.1.1
Summary: Reflex components
Project-URL: Documentation, https://phil65.github.io/reflexions/
Project-URL: Source, https://github.com/phil65/reflexions
Project-URL: Issues, https://github.com/phil65/reflexions/issues
Project-URL: Discussions, https://github.com/phil65/reflexions/discussions
Project-URL: Code coverage, https://app.codecov.io/gh/phil65/reflexions
Author-email: Philipp Temminghoff <philipptemminghoff@googlemail.com>
License: MIT License
License-File: LICENSE
Classifier: Development Status :: 4 - Beta
Classifier: Framework :: Pydantic
Classifier: Framework :: Pydantic :: 2
Classifier: Intended Audience :: Developers
Classifier: Operating System :: OS Independent
Classifier: Programming Language :: Python :: 3
Classifier: Programming Language :: Python :: 3 :: Only
Classifier: Programming Language :: Python :: 3.12
Classifier: Programming Language :: Python :: 3.13
Classifier: Programming Language :: Python :: 3.14
Classifier: Topic :: Documentation
Classifier: Topic :: Software Development
Classifier: Topic :: Utilities
Classifier: Typing :: Typed
Requires-Python: >=3.12
Requires-Dist: pydantic
Requires-Dist: reflex-chakra>=0.7.0
Requires-Dist: reflex>=0.7.4
